buycoins/__init__.py
buycoins/constants.py
buycoins/executor.py
buycoins/mutations.py
buycoins/queries.py
buycoins/utils.py
tests/__init__.py
tests/responses.py
tests/test_mutations.py
tests/test_queries.py
python_buycoins-1.0.dist-info/LICENSE
python_buycoins-1.0.dist-info/METADATA
python_buycoins-1.0.dist-info/WHEEL
python_buycoins-1.0.dist-info/top_level.txt
python_buycoins-1.0.dist-info/RECORD
