Metadata-Version: 2.1
Name: python-buycoins
Version: 1.0
Summary: BuyCoins API library
Home-page: https://github.com/Cimmanuel/python-buycoins
Author: Immanuel Kolapo
Author-email: immanuelcaspian@gmail.com
License: MIT
Platform: UNKNOWN
Classifier: License :: OSI Approved :: MIT License
Classifier: Programming Language :: Python :: 3.6
Classifier: Programming Language :: Python :: 3.7
Classifier: Programming Language :: Python :: 3.8
Classifier: Programming Language :: Python :: 3.9
Requires-Python: >=3.6
Requires-Dist: requests
Requires-Dist: python-decouple
